{
  "extends": [
    "tslint:recommended",
    "tslint-eslint-rules"
  ],
  "rules": {
    "curly": false,
    "no-default-export": true,
    "ter-indent": [true, 2],
    "object-curly-spacing": [true, "always", { "objectsInObjects": false }],
    "no-constant-condition": true,
    "no-extra-semi": true,
    "valid-typeof": true,
    "brace-style": [true, "1tbs", { "allowSingleLine": true }],
    "no-shadowed-variable": false,
    "variable-name": [true, "ban-keywords", "check-format", "allow-pascal-case", "allow-leading-underscore", "allow-trailing-underscore"],
    "linebreak-style": [true, "LF"],
    "array-type": [true, "array"],
    "quotemark": [true, "single", "jsx-double", "avoid-escape"],
    "interface-name": [true, "never-prefix"],
    "max-classes-per-file": false,
    "arrow-parens": false,
    "ordered-imports": false,
    "object-literal-sort-keys": false,
    "trailing-comma": false,
    "no-string-literal": false,
    "no-string-throw": true,
    "switch-default": false,
    "max-line-length": [true, 140],
    "completed-docs": true,
    "member-access": false,
    "prefer-method-signature": true,
    "arrow-return-shorthand": [true],
    "typedef": [true, "parameter"],
    "no-inferrable-types": [true, "ignore-params", "ignore-properties"],
    "promise-function-async": true,
    "no-reference": true,
    "unified-signatures": true,
    "indent": false,
    "eofline": [true],
    "no-magic-numbers": false,
    "no-unused-variable": [true, {"ignore-pattern": "^_"}],
    "member-ordering": [true, {
      "order": [
        "instance-field",
        "constructor",
        "instance-method",
        "static-field"
      ]
    }]
  }
}
